ipaffinity/__init__.py
ipaffinity/main.py
ipaffinity-0.0.0.dist-info/LICENSE
ipaffinity-0.0.0.dist-info/METADATA
ipaffinity-0.0.0.dist-info/WHEEL
ipaffinity-0.0.0.dist-info/RECORD
