Metadata-Version: 2.1
Name: ipaffinity
Version: 0.0.0
Summary: Phonetic similarity measurement between IPA strings
Home-page: https://github.com/hmonfette/ipaffinity
License: MIT
Author: hmonfette
Author-email: hugomonfette@hotmail.com
Requires-Python: >=3.11,<4.0
Classifier: License :: OSI Approved :: MIT License
Classifier: Programming Language :: Python :: 3
Classifier: Programming Language :: Python :: 3.11
Project-URL: Repository, https://github.com/hmonfette/ipaffinity
